s3autocp/__init__.py
s3autocp/s3autocp.py
s3autocp-0.4.0.dist-info/LICENSE
s3autocp-0.4.0.dist-info/METADATA
s3autocp-0.4.0.dist-info/WHEEL
s3autocp-0.4.0.dist-info/entry_points.txt
s3autocp-0.4.0.dist-info/top_level.txt
s3autocp-0.4.0.dist-info/RECORD
