Metadata-Version: 2.1
Name: s3autocp
Version: 0.4.0
Summary: A tool for copying build folders to S3 with guessed Content-Type and Cache-Control
Author-email: Jouni Tenhunen <jouni.tenhunen@nitor.com>, Kalle Ahlström <kalle.ahlstrom@nitor.com>
Project-URL: Homepage, https://github.com/NitorCreations/s3autocp
Classifier: Programming Language :: Python :: 3
Classifier: License :: OSI Approved :: Apache Software License
Classifier: Operating System :: OS Independent
Requires-Python: >=3.9
License-File: LICENSE
Requires-Dist: boto3
Requires-Dist: brotli
